.gitignore
.hgignore
CHANGES.txt
README.txt
bootstrap.py
buildout.cfg
setup.cfg
setup.py
src/minitage/__init__.py
src/minitage.recipe.egg-info/PKG-INFO
src/minitage.recipe.egg-info/SOURCES.txt
src/minitage.recipe.egg-info/dependency_links.txt
src/minitage.recipe.egg-info/entry_points.txt
src/minitage.recipe.egg-info/namespace_packages.txt
src/minitage.recipe.egg-info/not-zip-safe
src/minitage.recipe.egg-info/requires.txt
src/minitage.recipe.egg-info/top_level.txt
src/minitage/recipe/__init__.py